LICENSE
MANIFEST.in
README.md
README.rst
setup.py
redmon/__init__.py
redmon/conf.py
redmon.egg-info/PKG-INFO
redmon.egg-info/SOURCES.txt
redmon.egg-info/dependency_links.txt
redmon.egg-info/entry_points.txt
redmon.egg-info/requires.txt
redmon.egg-info/top_level.txt
redmon/cli/__init__.py
redmon/cli/cli.py