Metadata-Version: 1.1
Name: redmon
Version: 0.1.2
Summary: Monitor a Redis key
Home-page: https://github.com/swaathi/redmon
Author: Swaathi Kakarla
Author-email: swaathi@skcript.com
License: Copyright (c) 2016, Swaathi Kakarla
